LICENSE
README.md
setup.cfg
setup.py
polyloss/__init__.py
polyloss/polyloss.py
polyloss.egg-info/PKG-INFO
polyloss.egg-info/SOURCES.txt
polyloss.egg-info/dependency_links.txt
polyloss.egg-info/requires.txt
polyloss.egg-info/top_level.txt