Metadata-Version: 2.1
Name: polyloss
Version: 0.0.1
Summary: pytorch implementation of poly loss
Home-page: https://github.com/jahongir7174/PolyLoss
Author: Jahongir Yunusov
Author-email: jahongir7174@gmail.com
License: MIT
Platform: UNKNOWN
Classifier: License :: OSI Approved :: MIT License
Classifier: Programming Language :: Python :: 3.6
Classifier: Programming Language :: Python :: 3.9
